tests/__init__.py
tests/login_testcase.py
tests/test_cli_app.py
tests/test_cli_auth.py
tests/test_cli_completion.py
tests/test_cli_deck.py
tests/test_cli_helper.py
tests/test_cli_orga.py
tests/test_cli_project.py
tests/test_cli_ps.py
tests/test_cli_system.py
tests/test_context.py
unikube/__init__.py
unikube/__main__.py
unikube/commands.py
unikube/graphql_utils.py
unikube/helpers.py
unikube/settings.py
unikube/types.py
unikube/_backup/decorators.py
unikube/_backup/utils_project.py
unikube/authentication/__init__.py
unikube/authentication/authentication.py
unikube/authentication/login.html
unikube/authentication/types.py
unikube/authentication/web.py
unikube/cli/__init__.py
unikube/cli/app.py
unikube/cli/auth.py
unikube/cli/context.py
unikube/cli/deck.py
unikube/cli/helper.py
unikube/cli/orga.py
unikube/cli/project.py
unikube/cli/system.py
unikube/cli/unikube.py
unikube/cli/utils.py
unikube/cli/console/__init__.py
unikube/cli/console/container.py
unikube/cli/console/deck.py
unikube/cli/console/exit.py
unikube/cli/console/helpers.py
unikube/cli/console/input.py
unikube/cli/console/logger.py
unikube/cli/console/orga.py
unikube/cli/console/output.py
unikube/cli/console/project.py
unikube/completion/__init__.py
unikube/completion/completion.py
unikube/completion/templates.py
unikube/context/__init__.py
unikube/context/context.py
unikube/context/helper.py
unikube/context/types.py
unikube/keycloak/__init__.py
unikube/keycloak/permissions.py
unikube/local/__init__.py
unikube/local/dependency.py
unikube/local/exceptions.py
unikube/local/system.py
unikube/local/providers/__init__.py
unikube/local/providers/abstract_provider.py
unikube/local/providers/factory.py
unikube/local/providers/helper.py
unikube/local/providers/manager.py
unikube/local/providers/types.py
unikube/local/providers/k3d/__init__.py
unikube/local/providers/k3d/k3d.py
unikube/local/providers/k3d/storage.py
unikube/local/providers/k3d/types.py
unikube/storage/__init__.py
unikube/storage/general.py
unikube-1.2.9.dist-info/LICENSE
unikube-1.2.9.dist-info/METADATA
unikube-1.2.9.dist-info/WHEEL
unikube-1.2.9.dist-info/entry_points.txt
unikube-1.2.9.dist-info/top_level.txt
unikube-1.2.9.dist-info/RECORD
