Metadata-Version: 2.1
Name: unikube
Version: 1.2.9
Summary: This is the unikube.io command line interface
Home-page: https://github.com/unikubehq/cli
Author: Michael Schilonka
Author-email: michael@blueshoe.de
License: UNKNOWN
Project-URL: Source, https://github.com/unikubehq/cli
Project-URL: Documentation, https://cli.unikube.io
Project-URL: Bug Tracker, https://github.com/unikubehq/cli/issues
Platform: UNKNOWN
Classifier: Development Status :: 3 - Alpha
Classifier: Intended Audience :: Developers
Classifier: Topic :: Software Development :: Build Tools
Classifier: Programming Language :: Python :: 3.8
Requires-Python: ~=3.7
License-File: LICENSE
Requires-Dist: click (==8.0.4)
Requires-Dist: click-spinner (==0.1.10)
Requires-Dist: colorama (~=0.4.4)
Requires-Dist: inquirerpy (<0.4.0,>=0.2.4)
Requires-Dist: tabulate (~=0.8.9)
Requires-Dist: pydantic (<1.10.0,>=1.7.3)
Requires-Dist: pyyaml (>=5.4)
Requires-Dist: tinydb (<4.8.0,>=3.15.2)
Requires-Dist: requests (<2.28.0,>=2.25.1)
Requires-Dist: pyjwt[crypto] (<2.4.0,>=2.0.1)
Requires-Dist: gql (<3.1,>=3.0)
Requires-Dist: semantic-version (<2.10.0,>=2.8.4)
Requires-Dist: kubernetes (<22.0.0,>=11.0.0)
Requires-Dist: retrying (~=1.3.3)
Requires-Dist: oic (==1.3.0)
Requires-Dist: python-slugify (<6.2.0,>=5.0.2)
Requires-Dist: click-didyoumean (~=0.3.0)
Requires-Dist: requests-toolbelt (~=0.9.1)
